pyramid_oauthlib/__init__.py
pyramid_oauthlib/test_suite.py
pyramid_oauthlib-1.0.0.dist-info/LICENSE.txt
pyramid_oauthlib-1.0.0.dist-info/METADATA
pyramid_oauthlib-1.0.0.dist-info/WHEEL
pyramid_oauthlib-1.0.0.dist-info/top_level.txt
pyramid_oauthlib-1.0.0.dist-info/RECORD
