Metadata-Version: 2.1
Name: pyramid-oauthlib
Version: 1.0.0
Summary: Pyramid OAuthLib integration
Home-page: https://github.com/tilgovi/pyramid_oauthlib
Author: Randall Leeds
Author-email: tilgovi@hypothes.is
Keywords: web pyramid pylons oauth authentication
Classifier: Programming Language :: Python
Classifier: Programming Language :: Python :: 3
Classifier: Programming Language :: Python :: 3.7
Classifier: Programming Language :: Python :: 3.8
Classifier: Programming Language :: Python :: 3.9
Classifier: Programming Language :: Python :: 3.10
Classifier: Programming Language :: Python :: 3 :: Only
Classifier: Framework :: Pyramid
Classifier: Topic :: Internet :: WWW/HTTP
Classifier: Topic :: Internet :: WWW/HTTP :: WSGI :: Middleware
Requires-Python: >=3.7
License-File: LICENSE.txt
Requires-Dist: pyramid (>=1.4.0)
Requires-Dist: oauthlib (>=3)
